[
  {
    "remark": "okeish",
    "studentId": "5a8d682e5d9cd2686da1667b",
    "_id": "5a8d7a910d96ba7e47f77ec9",
    "color": "yellow",
    "date": "2018-02-20T00:00:00.000Z"
  },
  {
    "remark": "okeish",
    "studentId": "5a8d682e5d9cd2686da1667b",
    "_id": "5a8d7a910d96ba7e47f77eca",
    "color": "green",
    "date": "2018-02-21T00:00:00.000Z"
  },

  {
    "remark": "okeish",
    "studentId": "5a8d682e5d9cd2686da1667d",
    "_id": "5a8d7a910d96ba7e47f77ecd",
    "color": "red",
    "date": "2018-02-20T00:00:00.000Z"
  },
  {
    "remark": "okeish",
    "studentId": "5a8d682e5d9cd2686da1667d",
    "_id": "5a8d7a910d96ba7e47f77ed0",
    "color": "yellow",
    "date": "2018-02-21T00:00:00.000Z"
  },
  {
    "remark": "okeish",
    "studentId": "5a8d682e5d9cd2686da1667c",
    "_id": "5a8d7a910d96ba7e47f77ecb",
    "color": "yellow",
    "date": "2018-02-20T00:00:00.000Z"
  },
  {
    "remark": "okeish",
    "studentId": "5a8d682e5d9cd2686da1667c",
    "_id": "5a8d7a910d96ba7e47f77ed4",
    "color": "red",
    "date": "2018-02-21T00:00:00.000Z"
  },
  {
    "remark": "okeish",
    "studentId": "5a8d682e5d9cd2686da1667e",
    "_id": "5a8d7a910d96ba7e47f77ed2",
    "color": "green",
    "date": "2018-02-20T00:00:00.000Z"
  },
  {
      "remark": "okeish",
    "studentId": "5a8d682e5d9cd2686da1667e",
    "_id": "5a8d7a910d96ba7e47f77ece",
    "color": "yellow",
    "date": "2018-02-21T00:00:00.000Z"
  },
  {
    "remark": "okeish",
    "studentId": "5a8d682e5d9cd2686da1667f",
    "_id": "5a8d7a910d96ba7e47f77ed5",
    "color": "green",
    "date": "2018-02-20T00:00:00.000Z"
  },
  {
    "remark": "okeish",
    "studentId": "5a8d682e5d9cd2686da1667f",
    "_id": "5a8d7a910d96ba7e47f77ed3",
    "color": "red",
    "date": "2018-02-21T00:00:00.000Z"
  },
  {
    "remark": "okeish",
    "studentId": "5a8d682e5d9cd2686da16681",
    "_id": "5a8d7a910d96ba7e47f77ecc",
    "color": "green",
    "date": "2018-02-20T00:00:00.000Z"
  },
  {
    "remark": "okeish",
    "studentId":"5a8d682e5d9cd2686da16681",
    "_id": "5a8d7a910d96ba7e47f77ed1",
    "color": "green",
    "date": "2018-02-21T00:00:00.000Z"
  },
  {
    "remark": "okeish",
    "studentId": "5a8d682e5d9cd2686da16680",
    "_id": "5a8d7a910d96ba7e47f77ecf",
    "color": "yellow",
    "date": "2018-02-20T00:00:00.000Z"
  },
  {
    "remark": "okeish",
    "studentId": "5a8d682e5d9cd2686da16680",
    "_id": "5a8d7a910d96ba7e47f77ed6",
    "color": "red",
    "date": "2018-02-21T00:00:00.000Z"
  }

]
